xows/__init__.py
xows/__main__.py
xows/version.py
xows-1.0.5.dist-info/LICENSE
xows-1.0.5.dist-info/METADATA
xows-1.0.5.dist-info/WHEEL
xows-1.0.5.dist-info/entry_points.txt
xows-1.0.5.dist-info/top_level.txt
xows-1.0.5.dist-info/RECORD
