Metadata-Version: 2.1
Name: xows
Version: 1.0.5
Summary: XoWS library / cli tool
Home-page: https://github.com/cisco-ce/pyxows
Author: Morten Minde Neergaard
Author-email: mneergaa@cisco.com
License: MIT
Keywords: websocket jsonrpc
Platform: UNKNOWN
Classifier: Development Status :: 5 - Production/Stable
Classifier: Programming Language :: Python :: 3
Classifier: Topic :: Utilities
Classifier: Framework :: AsyncIO
Requires-Python: >=3.7
License-File: LICENSE
Requires-Dist: aiohttp (>=3.1)
Requires-Dist: click (>=6.0)
